incenp/__init__.py
incenp/plotting/__init__.py
incenp/plotting/bar.py
incenp/plotting/scatter.py
incenp/plotting/util.py
incenp.plotting-0.1.0.dist-info/AUTHORS
incenp.plotting-0.1.0.dist-info/COPYING
incenp.plotting-0.1.0.dist-info/METADATA
incenp.plotting-0.1.0.dist-info/WHEEL
incenp.plotting-0.1.0.dist-info/top_level.txt
incenp.plotting-0.1.0.dist-info/RECORD
