Metadata-Version: 2.1
Name: incenp.plotting
Version: 0.1.0
Summary: Incenp.org´s plotting helper library
Home-page: https://git.incenp.org/damien/pyplot
Author: Damien Goutte-Gattat
Author-email: dgouttegattat@incenp.org
License: UNKNOWN
Platform: UNKNOWN
Classifier: Development Status :: 3 - Alpha
Classifier: Intended Audience :: Developers
Classifier: License :: OSI Approved :: GNU General Public License v3 or later (GPLv3+)
Classifier: Programming Language :: Python :: 3.7
Classifier: Topic :: Scientific/Engineering :: Visualization
Classifier: Topic :: Software Development :: Libraries :: Python Modules
